LitPy/__init__.py
LitPy/module.py
LitPy/testing.py
horizon/__init__.py
horizon/module.py
horizon-beyond/__init__.py
horizon-beyond/module.py
litpy-0.1.1.dist-info/LICENSE
litpy-0.1.1.dist-info/METADATA
litpy-0.1.1.dist-info/WHEEL
litpy-0.1.1.dist-info/entry_points.txt
litpy-0.1.1.dist-info/top_level.txt
litpy-0.1.1.dist-info/RECORD
